trytond/modules/health_gyneco/COPYING
trytond/modules/health_gyneco/README.rst
trytond/modules/health_gyneco/__init__.py
trytond/modules/health_gyneco/data/gnuhealth_commands.xml
trytond/modules/health_gyneco/data/messages/messages.xml
trytond/modules/health_gyneco/exceptions.py
trytond/modules/health_gyneco/health_gyneco.py
trytond/modules/health_gyneco/health_gyneco_view.xml
trytond/modules/health_gyneco/icons/gnuhealth_obstetrics.svg
trytond/modules/health_gyneco/locale/ar.po
trytond/modules/health_gyneco/locale/de.po
trytond/modules/health_gyneco/locale/el.po
trytond/modules/health_gyneco/locale/eo.po
trytond/modules/health_gyneco/locale/es.po
trytond/modules/health_gyneco/locale/fr.po
trytond/modules/health_gyneco/locale/health_gyneco.pot
trytond/modules/health_gyneco/locale/it_IT.po
trytond/modules/health_gyneco/locale/ja_JP.po
trytond/modules/health_gyneco/locale/ka.po
trytond/modules/health_gyneco/locale/lo.po
trytond/modules/health_gyneco/locale/pt_BR.po
trytond/modules/health_gyneco/locale/sv.po
trytond/modules/health_gyneco/locale/tr.po
trytond/modules/health_gyneco/locale/uk.po
trytond/modules/health_gyneco/locale/zh_CN.po
trytond/modules/health_gyneco/pyproject.toml
trytond/modules/health_gyneco/security/access_rights.xml
trytond/modules/health_gyneco/tests/__init__.py
trytond/modules/health_gyneco/tests/test_health_gyneco.py
trytond/modules/health_gyneco/tryton.cfg
trytond/modules/health_gyneco/view/gnuhealth_colposcopy_history.xml
trytond/modules/health_gyneco/view/gnuhealth_colposcopy_history_tree.xml
trytond/modules/health_gyneco/view/gnuhealth_mammography_history.xml
trytond/modules/health_gyneco/view/gnuhealth_mammography_history_tree.xml
trytond/modules/health_gyneco/view/gnuhealth_menstrual_history.xml
trytond/modules/health_gyneco/view/gnuhealth_menstrual_history_tree.xml
trytond/modules/health_gyneco/view/gnuhealth_pap_history.xml
trytond/modules/health_gyneco/view/gnuhealth_pap_history_tree.xml
gnuhealth_gyneco-5.0.2.dist-info/METADATA
gnuhealth_gyneco-5.0.2.dist-info/WHEEL
gnuhealth_gyneco-5.0.2.dist-info/licenses/COPYING
gnuhealth_gyneco-5.0.2.dist-info/RECORD
